WSGIUtils-0.7.2.dist-info/DESCRIPTION.rst
WSGIUtils-0.7.2.dist-info/LICENSE.txt
WSGIUtils-0.7.2.dist-info/METADATA
WSGIUtils-0.7.2.dist-info/RECORD
WSGIUtils-0.7.2.dist-info/WHEEL
WSGIUtils-0.7.2.dist-info/metadata.json
WSGIUtils-0.7.2.dist-info/top_level.txt
wsgiutils/SessionClient.py
wsgiutils/SessionServer.py
wsgiutils/__init__.py
wsgiutils/wsgiAdaptor.py
wsgiutils/wsgiServer.py
