Metadata-Version: 2.0
Name: WSGIUtils
Version: 0.7.2
Summary: WSGI Utils are a collection of useful libraries for use in a WSGI environnment.
Home-page: https://www.owlfish.com/software/wsgiutils/index.html
Author: Colin Stewart
Author-email: colin@owlfish.com
License: BSD-3-Clause
Project-URL: Source Code, https://github.com/davidfraser/WSGIUtils/
Project-URL: Documentation, https://www.owlfish.com/software/wsgiutils/documentation/index.html
Platform: UNKNOWN
Classifier: Development Status :: 5 - Production/Stable
Classifier: Intended Audience :: Developers
Classifier: Natural Language :: English
Classifier: License :: OSI Approved :: BSD License
Classifier: Operating System :: OS Independent
Classifier: Programming Language :: Python
Classifier: Programming Language :: Python :: 2.6
Classifier: Programming Language :: Python :: 2.7
Classifier: Programming Language :: Python :: 2 :: Only
Classifier: Topic :: Internet :: WWW/HTTP :: WSGI
